transformer_builder/__init__.py
transformer_builder/attention/__init__.py
transformer_builder/attention/multi_head_attention.py
transformer_builder/attention/self_attention.py
transformer_builder/decoder/__init__.py
transformer_builder/decoder/builder.py
transformer_builder/decoder/decoder.py
transformer_builder/decoder/decoder_block.py
transformer_builder/encoder/__init__.py
transformer_builder/encoder/builder.py
transformer_builder/encoder/encoder.py
transformer_builder/encoder/encoder_block.py
transformer_builder/layers/__init__.py
transformer_builder/layers/residual_connection.py
transformer_builder/transformer/__init__.py
transformer_builder/transformer/builder.py
transformer_builder/transformer/decoder/__init__.py
transformer_builder/transformer/decoder/builder.py
transformer_builder/transformer/decoder/multi_head_cross_attention.py
transformer_builder/transformer/decoder/transformer_decoder.py
transformer_builder/transformer/decoder/transformer_decoder_block.py
transformer_builder/transformer/encoder/__init__.py
transformer_builder/transformer/encoder/builder.py
transformer_builder/transformer/encoder/transformer_encoder.py
transformer_builder/transformer/encoder/transformer_encoder_block.py
transformer_builder/transformer/transformer.py
transformer_builder-0.1.0.dist-info/LICENSE
transformer_builder-0.1.0.dist-info/METADATA
transformer_builder-0.1.0.dist-info/WHEEL
transformer_builder-0.1.0.dist-info/RECORD
