Metadata-Version: 2.1
Name: transformer-builder
Version: 0.1.0
Summary: This package provides builder-like API to create really flexible transformers using PyTorch
Home-page: https://github.com/MrKekovich/transformer-builder
License: BSD-3-Clause
Keywords: pytorch,transformer,ai
Author: MrKekovich
Author-email: mrkekovich.official@gmail.com
Requires-Python: >=3.8,<3.12
Classifier: Development Status :: 2 - Pre-Alpha
Classifier: Intended Audience :: Developers
Classifier: Intended Audience :: Science/Research
Classifier: License :: OSI Approved :: BSD License
Classifier: Operating System :: OS Independent
Classifier: Programming Language :: Python
Classifier: Programming Language :: Python :: 3
Classifier: Programming Language :: Python :: 3.8
Classifier: Programming Language :: Python :: 3.9
Classifier: Programming Language :: Python :: 3.10
Classifier: Programming Language :: Python :: 3.11
Classifier: Topic :: Scientific/Engineering :: Artificial Intelligence
Classifier: Topic :: Software Development :: Libraries :: Python Modules
Classifier: Typing :: Typed
Requires-Dist: torch (>=2.1.0,<3.0.0)
Project-URL: Bug Tracker, https://github.com/MrKekovich/transformer-builder/issues
Project-URL: Repository, https://github.com/MrKekovich/transformer-builder
